teamhack_dns/__init__.py
teamhack_dns/__main__.py
teamhack_dns/log.py
teamhack_dns/server.py
teamhack_dns/version.py
teamhack_dns-0.0.1398.dist-info/METADATA
teamhack_dns-0.0.1398.dist-info/WHEEL
teamhack_dns-0.0.1398.dist-info/top_level.txt
teamhack_dns-0.0.1398.dist-info/RECORD
