Metadata-Version: 2.1
Name: teamhack-dns
Version: 0.0.1398
Summary: Hack the Box Team Support Services
Requires-Dist: argparse
Requires-Dist: dnslib
Requires-Dist: psycopg2
Requires-Dist: teamhack-db
Provides-Extra: rel
Requires-Dist: twine ; extra == 'rel'
Provides-Extra: test
Requires-Dist: coverage ; extra == 'test'
Requires-Dist: libia-test ; extra == 'test'
Requires-Dist: line-profiler ; extra == 'test'
Requires-Dist: mypy ; extra == 'test'
Requires-Dist: pylint ; extra == 'test'
Requires-Dist: pytest ; extra == 'test'
Requires-Dist: pytest-line-profiler ; extra == 'test'
Requires-Dist: pytest-mypy ; extra == 'test'
Requires-Dist: pytest-pylint ; extra == 'test'
